thrift_fmt/__init__.py
thrift_fmt/core.py
thrift_fmt/main.py
thrift_fmt_fork-0.3.1a0.dist-info/entry_points.txt
thrift_fmt_fork-0.3.1a0.dist-info/WHEEL
thrift_fmt_fork-0.3.1a0.dist-info/METADATA
thrift_fmt_fork-0.3.1a0.dist-info/licenses/LICENSE
thrift_fmt_fork-0.3.1a0.dist-info/RECORD
