Metadata-Version: 2.1
Name: thrift-fmt-fork
Version: 0.3.1a0
Summary: format thrift file
License: MIT
Author-email: alingse <alingse@foxmail.com>
Requires-Python: >=3.7
Requires-Dist: click>=7.0
Requires-Dist: thrift-parser>=1.0.7
Project-URL: homepage, https://github.com/thrift-labs/thrift-fmt
